design/fifo.v
module fifo #(
    parameter DATA_WIDTH = 8,
    parameter ADDR_WIDTH = 4,
    parameter ALMOST_FULL_THRESH = 14
)(
    input  wire clk,
    input  wire rst_n,
    
    // Write
    input  wire i_wr_en,
    input  wire [DATA_WIDTH-1:0] i_wr_data,
    output wire o_full,
    output wire o_almost_full, 

    // Read
    input  wire i_rd_en,
    output wire [DATA_WIDTH-1:0] o_rd_data,
    output wire o_empty
);

    reg [DATA_WIDTH-1:0] mem [0:(1<<ADDR_WIDTH)-1]; 	// 8 x 16
    reg [ADDR_WIDTH-1:0] wr_ptr, rd_ptr;
    reg [ADDR_WIDTH:0] count; 

    // Write Logic
    always @(posedge clk or negedge rst_n) begin
        if (!rst_n) wr_ptr <= 0;
        else if (i_wr_en && !o_full) begin
            mem[wr_ptr] <= i_wr_data;
            wr_ptr <= wr_ptr + 1;
        end
    end

    // Read Logic
    always @(posedge clk or negedge rst_n) begin
        if (!rst_n) rd_ptr <= 0;
        else if (i_rd_en && !o_empty) begin
            rd_ptr <= rd_ptr + 1;
        end
    end

    // Counter Logic
    always @(posedge clk or negedge rst_n) begin
        if (!rst_n) count <= 0;
        else begin
            case ({i_wr_en && !o_full, i_rd_en && !o_empty})
                2'b10: count <= count + 1;
                2'b01: count <= count - 1;
                default: count <= count;
            endcase
        end
    end

    // Outputs
    assign o_rd_data     = mem[rd_ptr];
    assign o_full        = (count == (1 << ADDR_WIDTH));
    assign o_empty       = (count == 0);
    assign o_almost_full = (count >= ALMOST_FULL_THRESH);

endmodule

testbench/tb_fifo.sv
`timescale 1ns/1ps
`include "../design/fifo.v"

module tb_fifo;
	/// -----  Signals  ----- //
	reg clk;
	reg rst_n;
	reg i_wr_en;
	reg [7:0] i_wr_data;
	wire o_full;
	wire o_almost_full;
	reg i_rd_en;
	wire [7:0] o_rd_data;
	wire o_empty;

	// -----  Parameters  ----- //
	localparam CLK_PERIOD = 20;
	parameter DATA_WIDTH = 8;
    parameter ADDR_WIDTH = 4;
    parameter ALMOST_FULL_THRESH = 14;

	// -----  Instantiate DUT  ----- //
	fifo #(
        .DATA_WIDTH(DATA_WIDTH),
        .ADDR_WIDTH(ADDR_WIDTH),
        .ALMOST_FULL_THRESH(ALMOST_FULL_THRESH)
    ) inst_fifo (
        .clk(clk),
        .rst_n(rst_n),
        .i_wr_en(i_wr_en),
        .i_wr_data(i_wr_data),
        .o_full(o_full),
        .o_almost_full(o_almost_full),
        .i_rd_en(i_rd_en),
        .o_rd_data(o_rd_data),
        .o_empty(o_empty)
    );

	// -----  Clock Gen  ----- //
	initial begin
		clk = 0;
		forever #(CLK_PERIOD/2) clk = ~clk;
	end

	// -----  Task  ----- //
	// Task write to FIFO
	task write_fifo(input [7:0] data);
		begin
			if(o_full) begin
				$display("[WARNING] FIFO Full! Cannot write %h", data);
			end else begin
				@(negedge clk);
				i_wr_en = 1;
				i_wr_data = data;
				@(negedge clk);
				i_wr_en = 0;
			end
		end
	endtask

	// Task read and check
	task read_and_check(input [7:0] expected_data);
		begin
            if (o_empty) begin
                $error("[FAIL] FIFO Empty! Cannot read expected %h", expected_data);
            end else begin
                // FIFO: FWFT -> check data before pulse rd_en
                #1; 
                if (o_rd_data != expected_data) begin
                    $error("[FAIL] Data Mismatch! Expected: %h, Got: %h", expected_data, o_rd_data);
                end else begin
                    $display("[PASS] Read Data: %h (Match)", o_rd_data);
                end
                
                // pulse read -> pointer to next
                @(negedge clk);
                i_rd_en = 1;
                @(negedge clk);
                i_rd_en = 0;
            end
        end
	endtask

	///==============================================================================
	//  SECTION: MAIN TEST SCENARIO
	//==============================================================================
	integer i;
    initial begin
        $display("=== START FIFO TEST ===");
        
        // --- TC_01: Init & Reset ---
        rst_n = 0; i_wr_en = 0; i_rd_en = 0; i_wr_data = 0;
        #50;
        if (o_empty === 1 && o_full === 0) 
            $display("[PASS TC_01] Reset Check OK");
        else 
            $error("[FAIL TC_01] Reset Failed");
        rst_n = 1;
        #20;

        // --- TC_02: Basic Write & Read ---
        $display("\n--- TC_02: Write 0xAA, Read 0xAA ---");
        write_fifo(8'hAA);
        #20;
        if (o_empty === 0) $display("[INFO] FIFO not empty, good.");
        read_and_check(8'hAA);
        if (o_empty === 1) $display("[PASS TC_02] Empty again after read.");

        // --- TC_03 & TC_04: Fill FIFO & Check Flags ---
        $display("\n--- TC_03 & TC_04: Fill FIFO (16 items) ---");
        // Ghi 16 giá trị: 0x10, 0x11, ... 0x1F
        for (i = 0; i < 16; i = i + 1) begin
            write_fifo(8'h10 + i);
            // Check Almost at 14 (written 14 byte: index 0-13)
            if (i == 13) begin 
                #1; // Wait logic update
                if (o_almost_full) $display("[PASS TC_04] Almost Full Triggered at 14 items");
                else               $error("[FAIL TC_04] Almost Full MISSED at 14 items");
            end
        end

        #1;
        if (o_full) $display("[PASS TC_03] FIFO Full Flag OK");
        else        $error("[FAIL TC_03] FIFO Should be FULL now!");

        // Overflow protection
        write_fifo(8'h99); // not allow

        // --- TC_05: Empty FIFO & Verify Data ---
        $display("\n--- TC_05: Empty FIFO & Verify Order ---");
        for (i = 0; i < 16; i = i + 1) begin
            read_and_check(8'h10 + i); // Phải đọc ra đúng thứ tự 0x10 -> 0x1F
        end

        #1;
        if (o_empty) $display("[PASS TC_05] FIFO Empty Flag OK");
        else         $error("[FAIL TC_05] FIFO Should be EMPTY now!");

        // --- TC_06: POINTER ROLLOVER (Test vòng lặp) ---
        $display("\n--- TC_06: Pointer Rollover Test ---");
        // Now FIFO empty
        // Write 10 bytes, read 10 bytes
        // Total write 30 byte -> Pointer roll over at least once (Depth=16).
        for (integer k = 0; k < 3; k = k + 1) begin
            // Ghi 10
            for (i = 0; i < 10; i = i + 1) write_fifo(8'hA0 + k*16 + i);
            // Đọc 10
            for (i = 0; i < 10; i = i + 1) read_and_check(8'hA0 + k*16 + i);
        end
        $display("[PASS TC_06] Pointer Rollover OK");

        #50; rst_n = 0;
        #50; rst_n = 1;

        // --- TC_07: SIMULTANEOUS READ & WRITE (Vừa đọc vừa ghi) ---
        $display("\n--- TC_07: Simultaneous Read & Write ---");
        // 1. Write some bytes
        write_fifo(8'h11);
        write_fifo(8'h22);
        write_fifo(8'h33);
        // count = 3.

        // 2. Enable cả WR adn RD both
        @(negedge clk);
        i_wr_en = 1; i_wr_data = 8'h44; 
        i_rd_en = 1;

        #1;
        $display("[DEBUG] Checking Data NOW: %h", o_rd_data);
        
        if (o_rd_data == 8'h11) 
            $display("[PASS] Simultaneous Data Out OK (Got 0x11)");
        else 
            $error("[FAIL] Simult. Data mismatch. Expected 0x11, Got %h", o_rd_data);
        // -------------------------------------------------------

        @(negedge clk); // Data to 0x22
        i_wr_en = 0; i_rd_en = 0;
        
        #1;
        $display("[DEBUG] Data after clock: %h", o_rd_data); // 0x22

        // 3. Check logic:
        // - Count=3 (In 1, Out 1).
        // - Data out in this period: 0x11.
        // - Next byte in queue line: 0x22.
        // - Byte 0x44: last 
        
        #10;
        // Read to check order
        read_and_check(8'h22);
        read_and_check(8'h33);
        read_and_check(8'h44);
        
        if (o_empty) $display("[PASS TC_07] Simultaneous R/W Logic OK");
        else         $error("[FAIL TC_07] Count Logic wrong after Simult. R/W");

        
        // --- TC_08: RANDOM STRESS TEST (Tra tấn ngẫu nhiên) ---
        $display("\n--- TC_08: Random Stress Test ---");
        rst_n = 0; #10; rst_n = 1; #10; // Reset sạch sẽ
        
        // Random write, read or both
        // Run 1000 
        begin
            reg [7:0] queue [$]; // Goden Model
            reg [7:0] val_in, val_out, val_exp;
            reg do_wr, do_rd;
            
            repeat(1000) begin
                @(negedge clk);
                do_wr = $urandom_range(0, 1);
                do_rd = $urandom_range(0, 1); 
                val_in = $urandom;

                // Cập nhật tín hiệu
                i_wr_en = do_wr && !o_full;  // write if not full 
                i_rd_en = do_rd && !o_empty; // read if not empty 
                i_wr_data = val_in;

                // Update Golden Model (Queue Testbench)
                if (i_wr_en) queue.push_back(val_in);
                
                // Check read data
                if (i_rd_en) begin
                    // 1. Lấy giá trị kỳ vọng từ mô hình mẫu (Queue)
                    if (queue.size() == 0) begin
                        $error("[FAIL] Testbench Logic Error: Queue empty but i_rd_en is HIGH");
                    end else begin
                        val_exp = queue.pop_front();
                        
                        // 2. SO SÁNH NGAY LẬP TỨC (QUAN TRỌNG)
                        // Vì FIFO là FWFT, dữ liệu o_rd_data đang hiện sẵn ở đầu ra
                        // ngay lúc ta quyết định đọc (trước khi clock active).
                        #1; // Delay 1 xíu để tín hiệu ổn định
                        if (o_rd_data != val_exp) begin
                            $error("[FAIL TC_08] Data Mismatch! Expected: %h, Got: %h", val_exp, o_rd_data);
                        end else begin
                            $display("Good: %h", o_rd_data);
                        end
                    end
                end
            end
            i_wr_en = 0; i_rd_en = 0;
            $display("[PASS TC_08] Survived 1000 cycles of Random Stress");
        end
        
	
	   $display("\n=== ALL TESTS COMPLETED ===");
        $finish;
    end

    // Dump sóng
    initial begin
        $dumpfile("waveform/fifo.vcd");
        $dumpvars(0, tb_fifo);
    end
endmodule

testbench/waveform/fifo.vcd
$date
	Tue Dec 16 10:32:43 2025
$end
$version
	Icarus Verilog
$end
$timescale
	1ps
$end
$scope module tb_fifo $end
$var wire 8 ! o_rd_data [7:0] $end
$var wire 1 " o_full $end
$var wire 1 # o_empty $end
$var wire 1 $ o_almost_full $end
$var parameter 32 % ADDR_WIDTH $end
$var parameter 32 & ALMOST_FULL_THRESH $end
$var parameter 32 ' CLK_PERIOD $end
$var parameter 32 ( DATA_WIDTH $end
$var reg 1 ) clk $end
$var reg 1 * i_rd_en $end
$var reg 8 + i_wr_data [7:0] $end
$var reg 1 , i_wr_en $end
$var reg 1 - rst_n $end
$var integer 32 . i [31:0] $end
$scope module inst_fifo $end
$var wire 1 ) clk $end
$var wire 1 * i_rd_en $end
$var wire 8 / i_wr_data [7:0] $end
$var wire 1 , i_wr_en $end
$var wire 8 0 o_rd_data [7:0] $end
$var wire 1 - rst_n $end
$var wire 1 " o_full $end
$var wire 1 # o_empty $end
$var wire 1 $ o_almost_full $end
$var parameter 32 1 ADDR_WIDTH $end
$var parameter 32 2 ALMOST_FULL_THRESH $end
$var parameter 32 3 DATA_WIDTH $end
$var reg 5 4 count [4:0] $end
$var reg 4 5 rd_ptr [3:0] $end
$var reg 4 6 wr_ptr [3:0] $end
$upscope $end
$scope begin $ivl_for_loop0 $end
$var integer 32 7 k [31:0] $end
$upscope $end
$scope begin $unm_blk_21 $end
$var reg 1 8 do_rd $end
$var reg 1 9 do_wr $end
$var reg 8 : val_exp [7:0] $end
$var reg 8 ; val_in [7:0] $end
$upscope $end
$scope task read_and_check $end
$var reg 8 < expected_data [7:0] $end
$upscope $end
$scope task write_fifo $end
$var reg 8 = data [7:0] $end
$upscope $end
$upscope $end
$enddefinitions $end
$comment Show the parameter values. $end
$dumpall
b1000 3
b1110 2
b100 1
b1000 (
b10100 '
b1110 &
b100 %
$end
#0
$dumpvars
bx =
bx <
bx ;
bx :
x9
x8
bx 7
b0 6
b0 5
b0 4
bx 0
b0 /
bx .
0-
0,
b0 +
0*
0)
0$
1#
0"
bx !
$end
#10000
1)
#20000
0)
#30000
1)
#40000
0)
#50000
1)
1-
#60000
0)
#70000
1)
b10101010 =
#80000
b10101010 +
b10101010 /
1,
0)
#90000
0#
b1 4
b1 6
b10101010 !
b10101010 0
1)
#100000
0,
0)
#110000
1)
#120000
0)
b10101010 <
#130000
1)
#140000
1*
0)
#150000
bx !
bx 0
1#
b1 5
b0 4
1)
#160000
b10000 =
b0 .
0*
0)
#170000
1)
#180000
b10000 +
b10000 /
1,
0)
#190000
0#
b10 6
b10000 !
b10000 0
b1 4
1)
#200000
b10001 =
b1 .
0,
0)
#210000
1)
#220000
b10001 +
b10001 /
1,
0)
#230000
b11 6
b10 4
1)
#240000
b10010 =
b10 .
0,
0)
#250000
1)
#260000
b10010 +
b10010 /
1,
0)
#270000
b100 6
b11 4
1)
#280000
b10011 =
b11 .
0,
0)
#290000
1)
#300000
b10011 +
b10011 /
1,
0)
#310000
b101 6
b100 4
1)
#320000
b10100 =
b100 .
0,
0)
#330000
1)
#340000
b10100 +
b10100 /
1,
0)
#350000
b110 6
b101 4
1)
#360000
b10101 =
b101 .
0,
0)
#370000
1)
#380000
b10101 +
b10101 /
1,
0)
#390000
b111 6
b110 4
1)
#400000
b10110 =
b110 .
0,
0)
#410000
1)
#420000
b10110 +
b10110 /
1,
0)
#430000
b1000 6
b111 4
1)
#440000
b10111 =
b111 .
0,
0)
#450000
1)
#460000
b10111 +
b10111 /
1,
0)
#470000
b1001 6
b1000 4
1)
#480000
b11000 =
b1000 .
0,
0)
#490000
1)
#500000
b11000 +
b11000 /
1,
0)
#510000
b1010 6
b1001 4
1)
#520000
b11001 =
b1001 .
0,
0)
#530000
1)
#540000
b11001 +
b11001 /
1,
0)
#550000
b1011 6
b1010 4
1)
#560000
b11010 =
b1010 .
0,
0)
#570000
1)
#580000
b11010 +
b11010 /
1,
0)
#590000
b1100 6
b1011 4
1)
#600000
b11011 =
b1011 .
0,
0)
#610000
1)
#620000
b11011 +
b11011 /
1,
0)
#630000
b1101 6
b1100 4
1)
#640000
b11100 =
b1100 .
0,
0)
#650000
1)
#660000
b11100 +
b11100 /
1,
0)
#670000
b1110 6
b1101 4
1)
#680000
b11101 =
b1101 .
0,
0)
#690000
1)
#700000
b11101 +
b11101 /
1,
0)
#710000
1$
b1111 6
b1110 4
1)
#720000
0,
0)
#721000
b11110 =
b1110 .
#730000
1)
#740000
b11110 +
b11110 /
1,
0)
#750000
b0 6
b1111 4
1)
#760000
b11111 =
b1111 .
0,
0)
#770000
1)
#780000
b11111 +
b11111 /
1,
0)
#790000
1"
b1 6
b10000 4
1)
#800000
b10000 .
0,
0)
#801000
b10000 <
b0 .
b10011001 =
#810000
1)
#820000
1*
0)
#830000
b10001 !
b10001 0
0"
b10 5
b1111 4
1)
#840000
b10001 <
b1 .
0*
0)
#850000
1)
#860000
1*
0)
#870000
b10010 !
b10010 0
b11 5
b1110 4
1)
#880000
b10010 <
b10 .
0*
0)
#890000
1)
#900000
1*
0)
#910000
b10011 !
b10011 0
0$
b100 5
b1101 4
1)
#920000
b10011 <
b11 .
0*
0)
#930000
1)
#940000
1*
0)
#950000
b10100 !
b10100 0
b101 5
b1100 4
1)
#960000
b10100 <
b100 .
0*
0)
#970000
1)
#980000
1*
0)
#990000
b10101 !
b10101 0
b110 5
b1011 4
1)
#1000000
b10101 <
b101 .
0*
0)
#1010000
1)
#1020000
1*
0)
#1030000
b10110 !
b10110 0
b111 5
b1010 4
1)
#1040000
b10110 <
b110 .
0*
0)
#1050000
1)
#1060000
1*
0)
#1070000
b10111 !
b10111 0
b1000 5
b1001 4
1)
#1080000
b10111 <
b111 .
0*
0)
#1090000
1)
#1100000
1*
0)
#1110000
b11000 !
b11000 0
b1001 5
b1000 4
1)
#1120000
b11000 <
b1000 .
0*
0)
#1130000
1)
#1140000
1*
0)
#1150000
b11001 !
b11001 0
b1010 5
b111 4
1)
#1160000
b11001 <
b1001 .
0*
0)
#1170000
1)
#1180000
1*
0)
#1190000
b11010 !
b11010 0
b1011 5
b110 4
1)
#1200000
b11010 <
b1010 .
0*
0)
#1210000
1)
#1220000
1*
0)
#1230000
b11011 !
b11011 0
b1100 5
b101 4
1)
#1240000
b11011 <
b1011 .
0*
0)
#1250000
1)
#1260000
1*
0)
#1270000
b11100 !
b11100 0
b1101 5
b100 4
1)
#1280000
b11100 <
b1100 .
0*
0)
#1290000
1)
#1300000
1*
0)
#1310000
b11101 !
b11101 0
b1110 5
b11 4
1)
#1320000
b11101 <
b1101 .
0*
0)
#1330000
1)
#1340000
1*
0)
#1350000
b11110 !
b11110 0
b1111 5
b10 4
1)
#1360000
b11110 <
b1110 .
0*
0)
#1370000
1)
#1380000
1*
0)
#1390000
b11111 !
b11111 0
b0 5
b1 4
1)
#1400000
b11111 <
b1111 .
0*
0)
#1410000
1)
#1420000
1*
0)
#1430000
b10000 !
b10000 0
1#
b1 5
b0 4
1)
#1440000
b10000 .
0*
0)
#1441000
b10100000 =
b0 .
b0 7
#1450000
1)
#1460000
b10100000 +
b10100000 /
1,
0)
#1470000
0#
b10 6
b10100000 !
b10100000 0
b1 4
1)
#1480000
b10100001 =
b1 .
0,
0)
#1490000
1)
#1500000
b10100001 +
b10100001 /
1,
0)
#1510000
b11 6
b10 4
1)
#1520000
b10100010 =
b10 .
0,
0)
#1530000
1)
#1540000
b10100010 +
b10100010 /
1,
0)
#1550000
b100 6
b11 4
1)
#1560000
b10100011 =
b11 .
0,
0)
#1570000
1)
#1580000
b10100011 +
b10100011 /
1,
0)
#1590000
b101 6
b100 4
1)
#1600000
b10100100 =
b100 .
0,
0)
#1610000
1)
#1620000
b10100100 +
b10100100 /
1,
0)
#1630000
b110 6
b101 4
1)
#1640000
b10100101 =
b101 .
0,
0)
#1650000
1)
#1660000
b10100101 +
b10100101 /
1,
0)
#1670000
b111 6
b110 4
1)
#1680000
b10100110 =
b110 .
0,
0)
#1690000
1)
#1700000
b10100110 +
b10100110 /
1,
0)
#1710000
b1000 6
b111 4
1)
#1720000
b10100111 =
b111 .
0,
0)
#1730000
1)
#1740000
b10100111 +
b10100111 /
1,
0)
#1750000
b1001 6
b1000 4
1)
#1760000
b10101000 =
b1000 .
0,
0)
#1770000
1)
#1780000
b10101000 +
b10101000 /
1,
0)
#1790000
b1010 6
b1001 4
1)
#1800000
b10101001 =
b1001 .
0,
0)
#1810000
1)
#1820000
b10101001 +
b10101001 /
1,
0)
#1830000
b1011 6
b1010 4
1)
#1840000
b10100000 <
b0 .
0,
0)
#1850000
1)
#1860000
1*
0)
#1870000
b10100001 !
b10100001 0
b10 5
b1001 4
1)
#1880000
b10100001 <
b1 .
0*
0)
#1890000
1)
#1900000
1*
0)
#1910000
b10100010 !
b10100010 0
b11 5
b1000 4
1)
#1920000
b10100010 <
b10 .
0*
0)
#1930000
1)
#1940000
1*
0)
#1950000
b10100011 !
b10100011 0
b100 5
b111 4
1)
#1960000
b10100011 <
b11 .
0*
0)
#1970000
1)
#1980000
1*
0)
#1990000
b10100100 !
b10100100 0
b101 5
b110 4
1)
#2000000
b10100100 <
b100 .
0*
0)
#2010000
1)
#2020000
1*
0)
#2030000
b10100101 !
b10100101 0
b110 5
b101 4
1)
#2040000
b10100101 <
b101 .
0*
0)
#2050000
1)
#2060000
1*
0)
#2070000
b10100110 !
b10100110 0
b111 5
b100 4
1)
#2080000
b10100110 <
b110 .
0*
0)
#2090000
1)
#2100000
1*
0)
#2110000
b10100111 !
b10100111 0
b1000 5
b11 4
1)
#2120000
b10100111 <
b111 .
0*
0)
#2130000
1)
#2140000
1*
0)
#2150000
b10101000 !
b10101000 0
b1001 5
b10 4
1)
#2160000
b10101000 <
b1000 .
0*
0)
#2170000
1)
#2180000
1*
0)
#2190000
b10101001 !
b10101001 0
b1010 5
b1 4
1)
#2200000
b10101001 <
b1001 .
0*
0)
#2210000
1)
#2220000
1*
0)
#2230000
b11010 !
b11010 0
1#
b1011 5
b0 4
1)
#2240000
b10110000 =
b1 7
b0 .
0*
0)
#2250000
1)
#2260000
b10110000 +
b10110000 /
1,
0)
#2270000
0#
b1100 6
b10110000 !
b10110000 0
b1 4
1)
#2280000
b10110001 =
b1 .
0,
0)
#2290000
1)
#2300000
b10110001 +
b10110001 /
1,
0)
#2310000
b1101 6
b10 4
1)
#2320000
b10110010 =
b10 .
0,
0)
#2330000
1)
#2340000
b10110010 +
b10110010 /
1,
0)
#2350000
b1110 6
b11 4
1)
#2360000
b10110011 =
b11 .
0,
0)
#2370000
1)
#2380000
b10110011 +
b10110011 /
1,
0)
#2390000
b1111 6
b100 4
1)
#2400000
b10110100 =
b100 .
0,
0)
#2410000
1)
#2420000
b10110100 +
b10110100 /
1,
0)
#2430000
b0 6
b101 4
1)
#2440000
b10110101 =
b101 .
0,
0)
#2450000
1)
#2460000
b10110101 +
b10110101 /
1,
0)
#2470000
b1 6
b110 4
1)
#2480000
b10110110 =
b110 .
0,
0)
#2490000
1)
#2500000
b10110110 +
b10110110 /
1,
0)
#2510000
b10 6
b111 4
1)
#2520000
b10110111 =
b111 .
0,
0)
#2530000
1)
#2540000
b10110111 +
b10110111 /
1,
0)
#2550000
b11 6
b1000 4
1)
#2560000
b10111000 =
b1000 .
0,
0)
#2570000
1)
#2580000
b10111000 +
b10111000 /
1,
0)
#2590000
b100 6
b1001 4
1)
#2600000
b10111001 =
b1001 .
0,
0)
#2610000
1)
#2620000
b10111001 +
b10111001 /
1,
0)
#2630000
b101 6
b1010 4
1)
#2640000
b10110000 <
b0 .
0,
0)
#2650000
1)
#2660000
1*
0)
#2670000
b10110001 !
b10110001 0
b1100 5
b1001 4
1)
#2680000
b10110001 <
b1 .
0*
0)
#2690000
1)
#2700000
1*
0)
#2710000
b10110010 !
b10110010 0
b1101 5
b1000 4
1)
#2720000
b10110010 <
b10 .
0*
0)
#2730000
1)
#2740000
1*
0)
#2750000
b10110011 !
b10110011 0
b1110 5
b111 4
1)
#2760000
b10110011 <
b11 .
0*
0)
#2770000
1)
#2780000
1*
0)
#2790000
b10110100 !
b10110100 0
b1111 5
b110 4
1)
#2800000
b10110100 <
b100 .
0*
0)
#2810000
1)
#2820000
1*
0)
#2830000
b10110101 !
b10110101 0
b0 5
b101 4
1)
#2840000
b10110101 <
b101 .
0*
0)
#2850000
1)
#2860000
1*
0)
#2870000
b10110110 !
b10110110 0
b1 5
b100 4
1)
#2880000
b10110110 <
b110 .
0*
0)
#2890000
1)
#2900000
1*
0)
#2910000
b10110111 !
b10110111 0
b10 5
b11 4
1)
#2920000
b10110111 <
b111 .
0*
0)
#2930000
1)
#2940000
1*
0)
#2950000
b10111000 !
b10111000 0
b11 5
b10 4
1)
#2960000
b10111000 <
b1000 .
0*
0)
#2970000
1)
#2980000
1*
0)
#2990000
b10111001 !
b10111001 0
b100 5
b1 4
1)
#3000000
b10111001 <
b1001 .
0*
0)
#3010000
1)
#3020000
1*
0)
#3030000
b10100100 !
b10100100 0
1#
b101 5
b0 4
1)
#3040000
b11000000 =
b10 7
b0 .
0*
0)
#3050000
1)
#3060000
b11000000 +
b11000000 /
1,
0)
#3070000
0#
b110 6
b11000000 !
b11000000 0
b1 4
1)
#3080000
b11000001 =
b1 .
0,
0)
#3090000
1)
#3100000
b11000001 +
b11000001 /
1,
0)
#3110000
b111 6
b10 4
1)
#3120000
b11000010 =
b10 .
0,
0)
#3130000
1)
#3140000
b11000010 +
b11000010 /
1,
0)
#3150000
b1000 6
b11 4
1)
#3160000
b11000011 =
b11 .
0,
0)
#3170000
1)
#3180000
b11000011 +
b11000011 /
1,
0)
#3190000
b1001 6
b100 4
1)
#3200000
b11000100 =
b100 .
0,
0)
#3210000
1)
#3220000
b11000100 +
b11000100 /
1,
0)
#3230000
b1010 6
b101 4
1)
#3240000
b11000101 =
b101 .
0,
0)
#3250000
1)
#3260000
b11000101 +
b11000101 /
1,
0)
#3270000
b1011 6
b110 4
1)
#3280000
b11000110 =
b110 .
0,
0)
#3290000
1)
#3300000
b11000110 +
b11000110 /
1,
0)
#3310000
b1100 6
b111 4
1)
#3320000
b11000111 =
b111 .
0,
0)
#3330000
1)
#3340000
b11000111 +
b11000111 /
1,
0)
#3350000
b1101 6
b1000 4
1)
#3360000
b11001000 =
b1000 .
0,
0)
#3370000
1)
#3380000
b11001000 +
b11001000 /
1,
0)
#3390000
b1110 6
b1001 4
1)
#3400000
b11001001 =
b1001 .
0,
0)
#3410000
1)
#3420000
b11001001 +
b11001001 /
1,
0)
#3430000
b1111 6
b1010 4
1)
#3440000
b11000000 <
b0 .
0,
0)
#3450000
1)
#3460000
1*
0)
#3470000
b11000001 !
b11000001 0
b110 5
b1001 4
1)
#3480000
b11000001 <
b1 .
0*
0)
#3490000
1)
#3500000
1*
0)
#3510000
b11000010 !
b11000010 0
b111 5
b1000 4
1)
#3520000
b11000010 <
b10 .
0*
0)
#3530000
1)
#3540000
1*
0)
#3550000
b11000011 !
b11000011 0
b1000 5
b111 4
1)
#3560000
b11000011 <
b11 .
0*
0)
#3570000
1)
#3580000
1*
0)
#3590000
b11000100 !
b11000100 0
b1001 5
b110 4
1)
#3600000
b11000100 <
b100 .
0*
0)
#3610000
1)
#3620000
1*
0)
#3630000
b11000101 !
b11000101 0
b1010 5
b101 4
1)
#3640000
b11000101 <
b101 .
0*
0)
#3650000
1)
#3660000
1*
0)
#3670000
b11000110 !
b11000110 0
b1011 5
b100 4
1)
#3680000
b11000110 <
b110 .
0*
0)
#3690000
1)
#3700000
1*
0)
#3710000
b11000111 !
b11000111 0
b1100 5
b11 4
1)
#3720000
b11000111 <
b111 .
0*
0)
#3730000
1)
#3740000
1*
0)
#3750000
b11001000 !
b11001000 0
b1101 5
b10 4
1)
#3760000
b11001000 <
b1000 .
0*
0)
#3770000
1)
#3780000
1*
0)
#3790000
b11001001 !
b11001001 0
b1110 5
b1 4
1)
#3800000
b11001001 <
b1001 .
0*
0)
#3810000
1)
#3820000
1*
0)
#3830000
b10110100 !
b10110100 0
1#
b1111 5
b0 4
1)
#3840000
b11 7
b1010 .
0*
0)
#3850000
1)
#3860000
0)
#3870000
1)
#3880000
0)
#3890000
b10110101 !
b10110101 0
b0 5
b0 6
1)
0-
#3900000
0)
#3910000
1)
#3920000
0)
#3930000
1)
#3940000
b10001 +
b10001 /
1,
0)
b10001 =
1-
#3950000
0#
b1 6
b10001 !
b10001 0
b1 4
1)
#3960000
b100010 =
0,
0)
#3970000
1)
#3980000
b100010 +
b100010 /
1,
0)
#3990000
b10 6
b10 4
1)
#4000000
b110011 =
0,
0)
#4010000
1)
#4020000
b110011 +
b110011 /
1,
0)
#4030000
b11 6
b11 4
1)
#4040000
0,
0)
#4050000
1)
#4060000
1*
b1000100 +
b1000100 /
1,
0)
#4070000
b100010 !
b100010 0
b100 6
b1 5
1)
#4080000
0*
0,
0)
#4090000
1)
#4091000
b100010 <
#4100000
1*
0)
#4110000
b110011 !
b110011 0
b10 5
b10 4
1)
#4120000
b110011 <
0*
0)
#4130000
1)
#4140000
1*
0)
#4150000
b1000100 !
b1000100 0
b11 5
b1 4
1)
#4160000
b1000100 <
0*
0)
#4170000
1)
#4180000
1*
0)
#4190000
b10111001 !
b10111001 0
1#
b100 5
b0 4
1)
#4200000
b10001 !
b10001 0
b0 5
b0 6
0-
0*
0)
#4210000
1-
1)
#4220000
0)
#4230000
1)
#4240000
b1001 +
b1001 /
1,
b1001 ;
08
19
0)
#4250000
0#
b1 6
b1001 !
b1001 0
b1 4
1)
#4260000
b1001 :
b10001101 +
b10001101 /
1*
0,
b10001101 ;
18
09
0)
#4270000
1#
b100010 !
b100010 0
b0 4
b1 5
1)
#4280000
b1 +
b1 /
0*
b1 ;
08
0)
#4290000
1)
#4300000
b111101 +
b111101 /
1,
b111101 ;
18
19
0)
#4310000
0#
b1 4
b10 6
b111101 !
b111101 0
1)
#4320000
b111101 :
b11111001 +
b11111001 /
1*
b11111001 ;
0)
#4330000
b11111001 !
b11111001 0
b11 6
b10 5
1)
#4340000
b10101010 +
b10101010 /
0*
0,
b10101010 ;
08
09
0)
#4350000
1)
#4360000
b10010 +
b10010 /
1,
b10010 ;
19
0)
#4370000
b100 6
b10 4
1)
#4380000
b11111001 :
b11001110 +
b11001110 /
1*
b11001110 ;
18
0)
#4390000
b10010 !
b10010 0
b11 5
b101 6
1)
#4400000
b1011100 +
b1011100 /
0*
0,
b1011100 ;
08
09
0)
#4410000
1)
#4420000
b1100101 +
b1100101 /
b1100101 ;
0)
#4430000
1)
#4440000
b10010 :
b10000000 +
b10000000 /
1*
b10000000 ;
18
0)
#4450000
b11001110 !
b11001110 0
b100 5
b1 4
1)
#4460000
b11001110 :
b10011101 +
b10011101 /
1,
b10011101 ;
19
0)
#4470000
b10011101 !
b10011101 0
b101 5
b110 6
1)
#4480000
b1101 +
b1101 /
0*
0,
b1101 ;
08
09
0)
#4490000
1)
#4500000
b10011101 :
b11010101 +
b11010101 /
1*
b11010101 ;
18
0)
#4510000
1#
b11000001 !
b11000001 0
b0 4
b110 5
1)
#4520000
b11101 +
b11101 /
0*
b11101 ;
08
0)
#4530000
1)
#4540000
b1010 +
b1010 /
b1010 ;
18
0)
#4550000
1)
#4560000
b11110010 +
b11110010 /
b11110010 ;
08
0)
#4570000
1)
#4580000
b11011000 +
b11011000 /
1,
b11011000 ;
18
19
0)
#4590000
0#
b1 4
b111 6
b11011000 !
b11011000 0
1)
#4600000
b11101011 +
b11101011 /
b11101011 ;
08
0)
#4610000
b1000 6
b10 4
1)
#4620000
b11011000 :
b10101110 +
b10101110 /
1*
b10101110 ;
18
0)
#4630000
b11101011 !
b11101011 0
b111 5
b1001 6
1)
#4640000
b11101011 :
b1011 +
b1011 /
0,
b1011 ;
09
0)
#4650000
b10101110 !
b10101110 0
b1000 5
b1 4
1)
#4660000
b10101110 :
b1001111 +
b1001111 /
b1001111 ;
0)
#4670000
1#
b11000100 !
b11000100 0
b0 4
b1001 5
1)
#4680000
b1111110 +
b1111110 /
0*
b1111110 ;
0)
#4690000
1)
#4700000
b11011001 +
b11011001 /
1,
b11011001 ;
19
0)
#4710000
0#
b1 4
b1010 6
b11011001 !
b11011001 0
1)
#4720000
b11011001 :
b10011111 +
b10011111 /
1*
b10011111 ;
0)
#4730000
b10011111 !
b10011111 0
b1011 6
b1010 5
1)
#4740000
b10011111 :
b10110111 +
b10110111 /
b10110111 ;
0)
#4750000
b10110111 !
b10110111 0
b1011 5
b1100 6
1)
#4760000
b1011011 +
b1011011 /
0*
0,
b1011011 ;
08
09
0)
#4770000
1)
#4780000
b11010000 +
b11010000 /
1,
b11010000 ;
19
0)
