design/uart_tx.v
/////////////////////////////////////////////////////////////////////////////////
//
//  Module Name:  UART_TX
//  Project:      UART Implementation and Verification
//  Author:       DungPC
//  Date:         12/2025
//  Description:  Description here...
//
////////////////////////////////////////////////////////////////////////////////

module uart_tx (
	input wire clk,    // Clock
	input wire rst_n,  // Asynchronous reset active low
    input wire tx_tick,
	input wire [1:0] i_num_bit_data,
	input wire i_parity_en,
	input wire i_parity_type,
	input wire [7:0] i_data,
	input wire i_tx_start,
	output reg o_tx_done,
	input wire i_cts_n,
	output reg o_tx_serial
	
);

//==============================================================================
//  SECTION: Parameter
//==============================================================================
	localparam IDLE = 3'd0;
	localparam START = 3'd1;
	localparam DATA = 3'd2;
	localparam PARITY = 3'd3;
	localparam STOP = 3'd4;

//==============================================================================
//  SECTION: Internal
//==============================================================================
	reg [2:0] state, next_state;
	reg [2:0] bit_cnt;
	reg [7:0] shift_reg;
	reg tx_reg, tx_next;
	reg parity_bit;

	// bit limit for number of bits data -> 00:5,01:6,10:7,11:8
	wire [2:0] bit_limit = 3'd4 + {1'b0, i_num_bit_data};

//==============================================================================
//  SECTION: State Machine
//==============================================================================
	always @(posedge clk or negedge rst_n) begin
		if(!rst_n) begin
			state <= IDLE;
			tx_reg <= 1'b1;
			shift_reg <= 0;
			bit_cnt <= 0;
			o_tx_serial <= 1'b1;
			parity_bit <= 0;
		end else begin
			state <= next_state;
			tx_reg <= tx_next;
			o_tx_serial <= tx_reg;

			// -----	Update count/shift var at right state	-----
			if(state == IDLE && i_tx_start && !i_cts_n) begin
				// Load data to shift_reg
				shift_reg <= i_data;

				// Calculate parity
				case (bit_limit)
					2'b00: parity_bit <= ^i_data[4:0];
					2'b01: parity_bit <= ^i_data[5:0];
					2'b10: parity_bit <= ^i_data[6:0];
					2'b11: parity_bit <= ^i_data[7:0];				
				endcase

				// Parity type -> num bit 1 -> ODD: 1, EVEN:0
				if(i_parity_type) begin
					parity_bit <= ~parity_bit; 	// ODD parity
				end
			end else if(state == START) begin
				bit_cnt <= 0;
			end else if(state == DATA && tx_tick) begin
				shift_reg <= shift_reg >> 1; 	// shift right 1 bit
				bit_cnt <= bit_cnt + 1;
			end
		end
	end

//==============================================================================
//  SECTION: Next state logic
//==============================================================================
	always @(state or tx_tick or i_tx_start or i_cts_n or parity_bit or tx_reg) begin
		// initial
		next_state = state;
		tx_next = tx_reg;
		o_tx_done = 1'b0;     // default
		case(state)
			IDLE: begin
				tx_next = 1'b1;
				if(i_tx_start && !i_cts_n) begin
					next_state = START;
				end
			end
			START: begin
				if(tx_tick) begin
					tx_next = 1'b0;
					next_state = DATA;
				end
			end
			DATA: begin
                if(tx_tick) begin
                    tx_next = shift_reg[0];
                    if(bit_cnt == bit_limit) begin
                        if(i_parity_en) begin
                            next_state = PARITY;
                        end else begin
                            next_state = STOP;
                        end
                    end
                end
			end
			PARITY: begin
                if(tx_tick) begin
                    tx_next = parity_bit;
                    next_state = STOP;
                end
			end
			STOP: begin
                if(tx_tick) begin
                    tx_next = 1'b1;
                    next_state = IDLE;
                    o_tx_done = 1'b1;
                end
			end
			default: next_state = IDLE;
	   endcase
    end
endmodule

testbench/tb_uart_tx.sv
`timescale 1ns/1ps
`include "../design/uart_tx.v"

module tb_uart_tx;
    // ==============================================================================
    //  SECTION: Wire/Reg Declaration
    // ==============================================================================
    reg clk;      
    reg rst_n;    
    reg tx_tick;  
    
    // Configuration
    reg [1:0] i_num_bit_data; // 00:5, 01:6, 10:7, 11:8
    reg i_parity_en;
    reg i_parity_type;        // 0: Even, 1: Odd
    
    // Data & Control
    reg [7:0] i_data;
    reg i_tx_start;
    reg i_cts_n;              // 0: Clear to Send (OK), 1: Stop
    
    // Output
    wire o_tx_done;
    wire o_tx_serial;

    // parmeter for test
    parameter CLK_PERIOD = 20; // 50MHz

    // Baudrate simulation: 16 cycle clock = 1 tx_tick pulse
    localparam TICK_RATE = 16; 
    localparam BIT_TIME  = TICK_RATE * CLK_PERIOD; 

    // ==============================================================================
    //  SECTION: DUT Connection
    // ==============================================================================
    uart_tx inst_uart_tx (
        .clk           (clk),
        .rst_n         (rst_n),
        .tx_tick       (tx_tick),
        .i_num_bit_data(i_num_bit_data),
        .i_parity_en   (i_parity_en),
        .i_parity_type (i_parity_type),
        .i_data        (i_data),
        .i_tx_start    (i_tx_start),
        .i_cts_n       (i_cts_n),
        .o_tx_serial   (o_tx_serial),
        .o_tx_done     (o_tx_done)
    );

    // ==============================================================================
    //  SECTION: Clock & Baud Tick Generation
    // ==============================================================================
    // 1. Create Clock 50MHz
    initial begin
        clk = 0;
        forever #(CLK_PERIOD/2) clk = ~clk;
    end

    // 2. Create tx_tick
    // 16 clock cycle -> enable tx_tick in 1 cycle
    reg [3:0] tick_cnt;
    always @(posedge clk or negedge rst_n) begin
        if (!rst_n) begin
            tick_cnt <= 0;
            tx_tick  <= 0;
        end else begin
            if (tick_cnt == (TICK_RATE - 1)) begin
                tick_cnt <= 0;
                tx_tick  <= 1;
            end else begin
                tick_cnt <= tick_cnt + 1;
                tx_tick  <= 0;
            end
        end
    end

    // ==============================================================================
    //  SECTION: TASKS
    // ==============================================================================
    
    // Task send data
    task uart_drive_tx(input [7:0] data);
        begin
            @(posedge clk);
            i_data     <= data;
            i_tx_start <= 1;
            @(posedge clk);
            i_tx_start <= 0;
        end
    endtask

    // Task automatic check
    // Task will run parallel (fork-join) to watch o_tx_serial
    task uart_verify_serial_data(input [7:0] expected_data, input [1:0] num_bit, input parity_en, input parity_type);
        integer i;
        reg [7:0] received_data;
        reg       calc_p;
        integer   bit_limit;
        begin
            bit_limit = 5 + num_bit; // 00->5, 11->8
            received_data = 0;

            // 1. Wait Start Bit
            wait(o_tx_serial == 0);
            
            // 2. Jump to the middle of bit Start (0.5 * BIT_TIME)
            // simulation time, not clock cycle
            #(BIT_TIME / 2); 
            
            if (o_tx_serial !== 0) $display("[FAIL] Start bit unstable!");

            // 3. Jump to each bit to sample
            for (i = 0; i < bit_limit; i = i + 1) begin
                #(BIT_TIME); // jump 1 cycle
                received_data[i] = o_tx_serial;
            end

            // 4. Check Parity
            if (parity_en) begin
                #(BIT_TIME);
                // Calculate expected parity from received data
                case(num_bit)
                    2'b00: calc_p = ^received_data[4:0];
                    2'b01: calc_p = ^received_data[5:0];
                    2'b10: calc_p = ^received_data[6:0];
                    2'b11: calc_p = ^received_data[7:0];
                endcase
                if (parity_type) calc_p = ~calc_p; // Odd

                if (o_tx_serial !== calc_p) 
                    $error("[FAIL] Parity Mismatch! Exp: %b, Got: %b", calc_p, o_tx_serial);
                else 
                    $display("[INFO] Parity OK.");
            end

            // 5. Check Stop Bit
            #(BIT_TIME);
            if (o_tx_serial !== 1) 
                $error("[FAIL] Stop bit missing (Line not High)!");

            // 6. Compare Data
            // Mask bit (5 bit -> mask 3 high bit)
            case(num_bit)
                2'b00: received_data = received_data & 8'h1F;   
                2'b01: received_data = received_data & 8'h3F;
                2'b10: received_data = received_data & 8'h7F;
            endcase

            if (received_data === (expected_data & (8'hFF >> (8-bit_limit))))
                $display("[PASS] Data OK. Sent: 0x%h, Recv: 0x%h (Mode: %0d num_bit)", expected_data, received_data, bit_limit);
            else
                $error("[FAIL] Data Mismatch! Sent: 0x%h, Recv: 0x%h", expected_data, received_data);
        end
    endtask

    // ==============================================================================
    //  SECTION: STIMULUS
    // ==============================================================================
    initial begin
        // 1. Initial
        $display("================ UART TX TEST START ================");
        clk = 0;
        rst_n = 0;
        i_tx_start = 0;
        i_data = 0;
        i_cts_n = 0;
        
        // Default Config: 8N1
        i_num_bit_data = 2'b11; // 8 bit
        i_parity_en = 0;
        i_parity_type = 0;

        #100;
        rst_n = 1;
        #100;

        // ------------------------------------------------------------
        // CASE 1: 8N1 (8 Bit, No Parity) - Data 0x55
        // ------------------------------------------------------------
        $display("\n[CASE 1] Testing 8N1 with Data 0x55");
        fork
            begin
                uart_drive_tx(8'h55); // CPU send
                uart_verify_serial_data(8'h55, 2'b11, 0, 0);
            end
            begin
                wait(o_tx_done); 
            end
        join

        #200;

        // ------------------------------------------------------------
        // CASE 2: Test 5 bit Data (5N1) - Data 0x1F
        // ------------------------------------------------------------
        $display("\n[CASE 2] Testing 5N1 (Truncation check)");
        i_num_bit_data = 2'b00; // 5 bit mode
        fork
            begin
                uart_drive_tx(8'hFF); // send FF but expect 5 bit received (0x1F)
                uart_verify_serial_data(8'hFF, 2'b00, 0, 0);
            end
            begin
                wait(o_tx_done);
            end
        join
        
        #200;

        // ------------------------------------------------------------
        // CASE 3: Test Parity Even (8E1) - Data 0xAA
        // 0xAA (10101010) has 4 bit 1 -> Even Parity is 0
        // ------------------------------------------------------------
        $display("\n[CASE 3] Testing 8E1 (Even Parity)");
        i_num_bit_data = 2'b11; // 8 bit
        i_parity_en = 1;        // Enable Parity
        i_parity_type = 0;      // Even
        fork
            begin
                uart_drive_tx(8'hAA);
                uart_verify_serial_data(8'hAA, 2'b11, 1, 0);
            end
            begin
                wait(o_tx_done);
            end
        join
        
        #200;

        // ------------------------------------------------------------
        // CASE 4: Test Parity Odd (8O1) - Data 0xAA
        // 0xAA has 4 bit 1 -> Odd parity is 1
        // ------------------------------------------------------------
        $display("\n[CASE 4] Testing 8O1 (Odd Parity)");
        i_parity_type = 1; // Odd
        fork
            begin
                uart_drive_tx(8'hAA);
                uart_verify_serial_data(8'hAA, 2'b11, 1, 1);
            end
            begin
                wait(o_tx_done);
            end
        join
        
        #200;

        // ------------------------------------------------------------
        // CASE 5: Test Flow Control (CTS)
        // Pull CTS_N high (STOP), order to send, module must wait.
        // ------------------------------------------------------------
        $display("\n[CASE 5] Testing Flow Control (CTS Blocking)");
        i_parity_en = 0; // turn off parity
        
        i_cts_n = 1; // Peripheral is busy
        fork
            begin
                $display("   -> Asserting TX Start but CTS is HIGH (Busy)...");
                uart_drive_tx(8'h99);
            end
            // wait, o_tx_serial -> still 1 (IDLE), not done
            #1000;
            begin 
                 
                if (o_tx_serial == 0) $display("[FAIL] TX started while CTS was HIGH!");
                else                  $display("   -> TX held correctly.");
            end
            begin
                $display("   -> Releasing CTS (Active Low)...");
                i_cts_n = 0; // enable to send

                // Tx will run this time, check data for correctness
                uart_verify_serial_data(8'h99, 2'b11, 0, 0);
            end
            begin
                wait(o_tx_done);
            end
        join
        $display("[PASS] CTS Flow Control worked.");
        
        #500;
        $display("\n================ UART TX TEST DONE ================");
        $finish;
    end

    // gtkwave
    initial begin
        $dumpfile("waveform/uart_tx.vcd");
        $dumpvars(0, tb_uart_tx);
    end


endmodule

testbench/waveform/uart_tx.vcd
$date
	Fri Dec 19 15:16:11 2025
$end
$version
	Icarus Verilog
$end
$timescale
	1ps
$end
$scope module tb_uart_tx $end
$var wire 1 ! o_tx_serial $end
$var wire 1 " o_tx_done $end
$var parameter 64 # BIT_TIME $end
$var parameter 32 $ CLK_PERIOD $end
$var parameter 32 % TICK_RATE $end
$var reg 1 & clk $end
$var reg 1 ' i_cts_n $end
$var reg 8 ( i_data [7:0] $end
$var reg 2 ) i_num_bit_data [1:0] $end
$var reg 1 * i_parity_en $end
$var reg 1 + i_parity_type $end
$var reg 1 , i_tx_start $end
$var reg 1 - rst_n $end
$var reg 4 . tick_cnt [3:0] $end
$var reg 1 / tx_tick $end
$scope module inst_uart_tx $end
$var wire 1 & clk $end
$var wire 1 ' i_cts_n $end
$var wire 8 0 i_data [7:0] $end
$var wire 2 1 i_num_bit_data [1:0] $end
$var wire 1 * i_parity_en $end
$var wire 1 + i_parity_type $end
$var wire 1 , i_tx_start $end
$var wire 1 - rst_n $end
$var wire 1 / tx_tick $end
$var wire 3 2 bit_limit [2:0] $end
$var parameter 3 3 DATA $end
$var parameter 3 4 IDLE $end
$var parameter 3 5 PARITY $end
$var parameter 3 6 START $end
$var parameter 3 7 STOP $end
$var reg 3 8 bit_cnt [2:0] $end
$var reg 3 9 next_state [2:0] $end
$var reg 1 " o_tx_done $end
$var reg 1 ! o_tx_serial $end
$var reg 1 : parity_bit $end
$var reg 8 ; shift_reg [7:0] $end
$var reg 3 < state [2:0] $end
$var reg 1 = tx_next $end
$var reg 1 > tx_reg $end
$upscope $end
$scope task uart_drive_tx $end
$var reg 8 ? data [7:0] $end
$upscope $end
$scope task uart_verify_serial_data $end
$var reg 1 @ calc_p $end
$var reg 8 A expected_data [7:0] $end
$var reg 2 B num_bit [1:0] $end
$var reg 1 C parity_en $end
$var reg 1 D parity_type $end
$var reg 8 E received_data [7:0] $end
$var integer 32 F bit_limit [31:0] $end
$var integer 32 G i [31:0] $end
$upscope $end
$upscope $end
$enddefinitions $end
$comment Show the parameter values. $end
$dumpall
b100 7
b1 6
b11 5
b0 4
b10 3
b10000 %
b10100 $
b101000000 #
$end
#0
$dumpvars
bx G
bx F
bx E
xD
xC
bx B
bx A
x@
bx ?
1>
1=
b0 <
b0 ;
0:
b0 9
b0 8
b111 2
b11 1
b0 0
0/
b0 .
0-
0,
0+
0*
b11 )
b0 (
0'
0&
0"
1!
$end
#10000
1&
#20000
0&
#30000
1&
#40000
0&
#50000
1&
#60000
0&
#70000
1&
#80000
0&
#90000
1&
#100000
0&
1-
#110000
b1 .
1&
#120000
0&
#130000
b10 .
1&
#140000
0&
#150000
b11 .
1&
#160000
0&
#170000
b100 .
1&
#180000
0&
#190000
b101 .
1&
#200000
0&
b1010101 ?
#210000
b1 9
b110 .
1,
b1010101 (
b1010101 0
1&
#220000
0&
#230000
b1010101 ;
b1 <
b111 .
0,
b0 E
b1000 F
0D
0C
b11 B
b1010101 A
1&
#240000
0&
#250000
b1000 .
1&
#260000
0&
#270000
b1001 .
1&
#280000
0&
#290000
b1010 .
1&
#300000
0&
#310000
b1011 .
1&
#320000
0&
#330000
b1100 .
1&
#340000
0&
#350000
b1101 .
1&
#360000
0&
#370000
b1110 .
1&
#380000
0&
#390000
b1111 .
1&
#400000
0&
#410000
b10 9
0=
1/
b0 .
1&
#420000
0&
#430000
0>
b10 <
0/
b1 .
1&
#440000
0&
#450000
b10 .
0!
1&
#460000
0&
#470000
b11 .
1&
#480000
0&
#490000
b100 .
1&
#500000
0&
#510000
b101 .
1&
#520000
0&
#530000
b110 .
1&
#540000
0&
#550000
b111 .
1&
#560000
0&
#570000
b1000 .
1&
#580000
0&
#590000
b1001 .
1&
#600000
0&
#610000
b1010 .
1&
b0 G
#620000
0&
#630000
b1011 .
1&
#640000
0&
#650000
b1100 .
1&
#660000
0&
#670000
b1101 .
1&
#680000
0&
#690000
b1110 .
1&
#700000
0&
#710000
b1111 .
1&
#720000
0&
#730000
1=
1/
b0 .
1&
#740000
0&
#750000
b1 8
b101010 ;
1>
0/
b1 .
1&
#760000
0&
#770000
b10 .
1!
1&
#780000
0&
#790000
b11 .
1&
#800000
0&
#810000
b100 .
1&
#820000
0&
#830000
b101 .
1&
#840000
0&
#850000
b110 .
1&
#860000
0&
#870000
b111 .
1&
#880000
0&
#890000
b1000 .
1&
#900000
0&
#910000
b1001 .
1&
#920000
0&
#930000
b1010 .
1&
b1 G
b1 E
#940000
0&
#950000
b1011 .
1&
#960000
0&
#970000
b1100 .
1&
#980000
0&
#990000
b1101 .
1&
#1000000
0&
#1010000
b1110 .
1&
#1020000
0&
#1030000
b1111 .
1&
#1040000
0&
#1050000
0=
1/
b0 .
1&
#1060000
0&
#1070000
b10 8
b10101 ;
0>
0/
b1 .
1&
#1080000
0&
#1090000
b10 .
0!
1&
#1100000
0&
#1110000
b11 .
1&
#1120000
0&
#1130000
b100 .
1&
#1140000
0&
#1150000
b101 .
1&
#1160000
0&
#1170000
b110 .
1&
#1180000
0&
#1190000
b111 .
1&
#1200000
0&
#1210000
b1000 .
1&
#1220000
0&
#1230000
b1001 .
1&
#1240000
0&
#1250000
b1010 .
1&
b10 G
#1260000
0&
#1270000
b1011 .
1&
#1280000
0&
#1290000
b1100 .
1&
#1300000
0&
#1310000
b1101 .
1&
#1320000
0&
#1330000
b1110 .
1&
#1340000
0&
#1350000
b1111 .
1&
#1360000
0&
#1370000
1=
1/
b0 .
1&
#1380000
0&
#1390000
b11 8
b1010 ;
1>
0/
b1 .
1&
#1400000
0&
#1410000
b10 .
1!
1&
#1420000
0&
#1430000
b11 .
1&
#1440000
0&
#1450000
b100 .
1&
#1460000
0&
#1470000
b101 .
1&
#1480000
0&
#1490000
b110 .
1&
#1500000
0&
#1510000
b111 .
1&
#1520000
0&
#1530000
b1000 .
1&
#1540000
0&
#1550000
b1001 .
1&
#1560000
0&
#1570000
b1010 .
1&
b11 G
b101 E
#1580000
0&
#1590000
b1011 .
1&
#1600000
0&
#1610000
b1100 .
1&
#1620000
0&
#1630000
b1101 .
1&
#1640000
0&
#1650000
b1110 .
1&
#1660000
0&
#1670000
b1111 .
1&
#1680000
0&
#1690000
0=
1/
b0 .
1&
#1700000
0&
#1710000
b100 8
b101 ;
0>
0/
b1 .
1&
#1720000
0&
#1730000
b10 .
0!
1&
#1740000
0&
#1750000
b11 .
1&
#1760000
0&
#1770000
b100 .
1&
#1780000
0&
#1790000
b101 .
1&
#1800000
0&
#1810000
b110 .
1&
#1820000
0&
#1830000
b111 .
1&
#1840000
0&
#1850000
b1000 .
1&
#1860000
0&
#1870000
b1001 .
1&
#1880000
0&
#1890000
b1010 .
1&
b100 G
#1900000
0&
#1910000
b1011 .
1&
#1920000
0&
#1930000
b1100 .
1&
#1940000
0&
#1950000
b1101 .
1&
#1960000
0&
#1970000
b1110 .
1&
#1980000
0&
#1990000
b1111 .
1&
#2000000
0&
#2010000
1=
1/
b0 .
1&
#2020000
0&
#2030000
b101 8
b10 ;
1>
0/
b1 .
1&
#2040000
0&
#2050000
b10 .
1!
1&
#2060000
0&
#2070000
b11 .
1&
#2080000
0&
#2090000
b100 .
1&
#2100000
0&
#2110000
b101 .
1&
#2120000
0&
#2130000
b110 .
1&
#2140000
0&
#2150000
b111 .
1&
#2160000
0&
#2170000
b1000 .
1&
#2180000
0&
#2190000
b1001 .
1&
#2200000
0&
#2210000
b1010 .
1&
b101 G
b10101 E
#2220000
0&
#2230000
b1011 .
1&
#2240000
0&
#2250000
b1100 .
1&
#2260000
0&
#2270000
b1101 .
1&
#2280000
0&
#2290000
b1110 .
1&
#2300000
0&
#2310000
b1111 .
1&
#2320000
0&
#2330000
0=
1/
b0 .
1&
#2340000
0&
#2350000
b110 8
b1 ;
0>
0/
b1 .
1&
#2360000
0&
#2370000
b10 .
0!
1&
#2380000
0&
#2390000
b11 .
1&
#2400000
0&
#2410000
b100 .
1&
#2420000
0&
#2430000
b101 .
1&
#2440000
0&
#2450000
b110 .
1&
#2460000
0&
#2470000
b111 .
1&
#2480000
0&
#2490000
b1000 .
1&
#2500000
0&
#2510000
b1001 .
1&
#2520000
0&
#2530000
b1010 .
1&
b110 G
#2540000
0&
#2550000
b1011 .
1&
#2560000
0&
#2570000
b1100 .
1&
#2580000
0&
#2590000
b1101 .
1&
#2600000
0&
#2610000
b1110 .
1&
#2620000
0&
#2630000
b1111 .
1&
#2640000
0&
#2650000
1=
1/
b0 .
1&
#2660000
0&
#2670000
b111 8
b0 ;
1>
0/
b1 .
1&
#2680000
0&
#2690000
b10 .
1!
1&
#2700000
0&
#2710000
b11 .
1&
#2720000
0&
#2730000
b100 .
1&
#2740000
0&
#2750000
b101 .
1&
#2760000
0&
#2770000
b110 .
1&
#2780000
0&
#2790000
b111 .
1&
#2800000
0&
#2810000
b1000 .
1&
#2820000
0&
#2830000
b1001 .
1&
#2840000
0&
#2850000
b1010 .
1&
b111 G
b1010101 E
#2860000
0&
#2870000
b1011 .
1&
#2880000
0&
#2890000
b1100 .
1&
#2900000
0&
#2910000
b1101 .
1&
#2920000
0&
#2930000
b1110 .
1&
#2940000
0&
#2950000
b1111 .
1&
#2960000
0&
#2970000
b100 9
0=
1/
b0 .
1&
#2980000
0&
#2990000
b0 8
0>
b100 <
0/
b1 .
1&
#3000000
0&
#3010000
b10 .
0!
1&
#3020000
0&
#3030000
b11 .
1&
#3040000
0&
#3050000
b100 .
1&
#3060000
0&
#3070000
b101 .
1&
#3080000
0&
#3090000
b110 .
1&
#3100000
0&
#3110000
b111 .
1&
#3120000
0&
#3130000
b1000 .
1&
#3140000
0&
#3150000
b1001 .
1&
#3160000
0&
#3170000
b1010 .
1&
b1000 G
#3180000
0&
#3190000
b1011 .
1&
#3200000
0&
#3210000
b1100 .
1&
#3220000
0&
#3230000
b1101 .
1&
#3240000
0&
#3250000
b1110 .
1&
#3260000
0&
#3270000
b1111 .
1&
#3280000
0&
#3290000
1"
b0 9
1=
1/
b0 .
1&
#3300000
0&
#3310000
0"
1>
b0 <
0/
b1 .
1&
#3320000
0&
#3330000
b10 .
1!
1&
#3340000
0&
#3350000
b11 .
1&
#3360000
0&
#3370000
b100 .
1&
#3380000
0&
#3390000
b101 .
1&
#3400000
0&
#3410000
b110 .
1&
#3420000
0&
#3430000
b111 .
1&
#3440000
0&
#3450000
b1000 .
1&
#3460000
0&
#3470000
b1001 .
1&
#3480000
0&
#3490000
b1010 .
1&
#3500000
0&
#3510000
b1011 .
1&
#3520000
0&
#3530000
b1100 .
1&
#3540000
0&
#3550000
b1101 .
1&
#3560000
0&
#3570000
b1110 .
1&
#3580000
0&
#3590000
b1111 .
1&
#3600000
0&
#3610000
1/
b0 .
1&
#3620000
0&
#3630000
0/
b1 .
1&
#3640000
0&
#3650000
b10 .
1&
#3660000
0&
#3670000
b11 .
1&
#3680000
0&
#3690000
b1 9
b100 .
1,
b11111111 (
b11111111 0
b100 2
1&
b11111111 ?
b0 )
b0 1
#3700000
0&
#3710000
b11111111 ;
b1 <
b101 .
0,
b0 E
b101 F
b0 B
b11111111 A
1&
#3720000
0&
#3730000
b110 .
1&
#3740000
0&
#3750000
b111 .
1&
#3760000
0&
#3770000
b1000 .
1&
#3780000
0&
#3790000
b1001 .
1&
#3800000
0&
#3810000
b1010 .
1&
#3820000
0&
#3830000
b1011 .
1&
#3840000
0&
#3850000
b1100 .
1&
#3860000
0&
#3870000
b1101 .
1&
#3880000
0&
#3890000
b1110 .
1&
#3900000
0&
#3910000
b1111 .
1&
#3920000
0&
#3930000
b10 9
0=
1/
b0 .
1&
#3940000
0&
#3950000
0>
b10 <
0/
b1 .
1&
#3960000
0&
#3970000
b10 .
0!
1&
#3980000
0&
#3990000
b11 .
1&
#4000000
0&
#4010000
b100 .
1&
#4020000
0&
#4030000
b101 .
1&
#4040000
0&
#4050000
b110 .
1&
#4060000
0&
#4070000
b111 .
1&
#4080000
0&
#4090000
b1000 .
1&
#4100000
0&
#4110000
b1001 .
1&
#4120000
0&
#4130000
b1010 .
1&
b0 G
#4140000
0&
#4150000
b1011 .
1&
#4160000
0&
#4170000
b1100 .
1&
#4180000
0&
#4190000
b1101 .
1&
#4200000
0&
#4210000
b1110 .
1&
#4220000
0&
#4230000
b1111 .
1&
#4240000
0&
#4250000
1=
1/
b0 .
1&
#4260000
0&
#4270000
b1 8
b1111111 ;
1>
0/
b1 .
1&
#4280000
0&
#4290000
b10 .
1!
1&
#4300000
0&
#4310000
b11 .
1&
#4320000
0&
#4330000
b100 .
1&
#4340000
0&
#4350000
b101 .
1&
#4360000
0&
#4370000
b110 .
1&
#4380000
0&
#4390000
b111 .
1&
#4400000
0&
#4410000
b1000 .
1&
#4420000
0&
#4430000
b1001 .
1&
#4440000
0&
#4450000
b1010 .
1&
b1 G
b1 E
#4460000
0&
#4470000
b1011 .
1&
#4480000
0&
#4490000
b1100 .
1&
#4500000
0&
#4510000
b1101 .
1&
#4520000
0&
#4530000
b1110 .
1&
#4540000
0&
#4550000
b1111 .
1&
#4560000
0&
#4570000
1/
b0 .
1&
#4580000
0&
#4590000
b10 8
b111111 ;
0/
b1 .
1&
#4600000
0&
#4610000
b10 .
1&
#4620000
0&
#4630000
b11 .
1&
#4640000
0&
#4650000
b100 .
1&
#4660000
0&
#4670000
b101 .
1&
#4680000
0&
#4690000
b110 .
1&
#4700000
0&
#4710000
b111 .
1&
#4720000
0&
#4730000
b1000 .
1&
#4740000
0&
#4750000
b1001 .
1&
#4760000
0&
#4770000
b1010 .
1&
b10 G
b11 E
#4780000
0&
#4790000
b1011 .
1&
#4800000
0&
#4810000
b1100 .
1&
#4820000
0&
#4830000
b1101 .
1&
#4840000
0&
#4850000
b1110 .
1&
#4860000
0&
#4870000
b1111 .
1&
#4880000
0&
#4890000
1/
b0 .
1&
#4900000
0&
#4910000
b11 8
b11111 ;
0/
b1 .
1&
#4920000
0&
#4930000
b10 .
1&
#4940000
0&
#4950000
b11 .
1&
#4960000
0&
#4970000
b100 .
1&
#4980000
0&
#4990000
b101 .
1&
#5000000
0&
#5010000
b110 .
1&
#5020000
0&
#5030000
b111 .
1&
#5040000
0&
#5050000
b1000 .
1&
#5060000
0&
#5070000
b1001 .
1&
#5080000
0&
#5090000
b1010 .
1&
b11 G
b111 E
#5100000
0&
#5110000
b1011 .
1&
#5120000
0&
#5130000
b1100 .
1&
#5140000
0&
#5150000
b1101 .
1&
#5160000
0&
#5170000
b1110 .
1&
#5180000
0&
#5190000
b1111 .
1&
#5200000
0&
#5210000
1/
b0 .
1&
#5220000
0&
#5230000
b100 8
b1111 ;
0/
b1 .
1&
#5240000
0&
#5250000
b10 .
1&
#5260000
0&
#5270000
b11 .
1&
#5280000
0&
#5290000
b100 .
1&
#5300000
0&
#5310000
b101 .
1&
#5320000
0&
#5330000
b110 .
1&
#5340000
0&
#5350000
b111 .
1&
#5360000
0&
#5370000
b1000 .
1&
#5380000
0&
#5390000
b1001 .
1&
#5400000
0&
#5410000
b1010 .
1&
b100 G
b1111 E
#5420000
0&
#5430000
b1011 .
1&
#5440000
0&
#5450000
b1100 .
1&
#5460000
0&
#5470000
b1101 .
1&
#5480000
0&
#5490000
b1110 .
1&
#5500000
0&
#5510000
b1111 .
1&
#5520000
0&
#5530000
b100 9
1/
b0 .
1&
#5540000
0&
#5550000
b101 8
b111 ;
b100 <
0/
b1 .
1&
#5560000
0&
#5570000
b10 .
1&
#5580000
0&
#5590000
b11 .
1&
#5600000
0&
#5610000
b100 .
1&
#5620000
0&
#5630000
b101 .
1&
#5640000
0&
#5650000
b110 .
1&
#5660000
0&
#5670000
b111 .
1&
#5680000
0&
#5690000
b1000 .
1&
#5700000
0&
#5710000
b1001 .
1&
#5720000
0&
#5730000
b1010 .
1&
b101 G
b11111 E
#5740000
0&
#5750000
b1011 .
1&
#5760000
0&
#5770000
b1100 .
1&
#5780000
0&
#5790000
b1101 .
1&
#5800000
0&
#5810000
b1110 .
1&
#5820000
0&
#5830000
b1111 .
1&
#5840000
0&
#5850000
1"
b0 9
1/
b0 .
1&
#5860000
0&
#5870000
0"
b0 <
0/
b1 .
1&
#5880000
0&
#5890000
b10 .
1&
#5900000
0&
#5910000
b11 .
1&
#5920000
0&
#5930000
b100 .
1&
#5940000
0&
#5950000
b101 .
1&
#5960000
0&
#5970000
b110 .
1&
#5980000
0&
#5990000
b111 .
1&
#6000000
0&
#6010000
b1000 .
1&
#6020000
0&
#6030000
b1001 .
1&
#6040000
0&
#6050000
b1010 .
1&
#6060000
0&
#6070000
b1011 .
1&
#6080000
0&
#6090000
b1100 .
1&
#6100000
0&
#6110000
b1101 .
1&
#6120000
0&
#6130000
b1110 .
1&
#6140000
0&
#6150000
b1111 .
1&
#6160000
0&
#6170000
1/
b0 .
1&
#6180000
0&
#6190000
0/
b1 .
1&
#6200000
0&
#6210000
b10 .
1&
#6220000
0&
#6230000
b11 .
1&
#6240000
0&
#6250000
b1 9
b100 .
1,
b10101010 (
b10101010 0
b111 2
1&
b10101010 ?
1*
b11 )
b11 1
#6260000
0&
#6270000
b10101010 ;
b1 <
b101 .
0,
b0 E
b1000 F
1C
b11 B
b10101010 A
1&
#6280000
0&
#6290000
b110 .
b0 8
1&
#6300000
0&
#6310000
b111 .
1&
#6320000
0&
#6330000
b1000 .
1&
#6340000
0&
#6350000
b1001 .
1&
#6360000
0&
#6370000
b1010 .
1&
#6380000
0&
#6390000
b1011 .
1&
#6400000
0&
#6410000
b1100 .
1&
#6420000
0&
#6430000
b1101 .
1&
#6440000
0&
#6450000
b1110 .
1&
#6460000
0&
#6470000
b1111 .
1&
#6480000
0&
#6490000
b10 9
0=
1/
b0 .
1&
#6500000
0&
#6510000
0>
b10 <
0/
b1 .
1&
#6520000
0&
#6530000
b10 .
0!
1&
#6540000
0&
#6550000
b11 .
1&
#6560000
0&
#6570000
b100 .
1&
#6580000
0&
#6590000
b101 .
1&
#6600000
0&
#6610000
b110 .
1&
#6620000
0&
#6630000
b111 .
1&
#6640000
0&
#6650000
b1000 .
1&
#6660000
0&
#6670000
b1001 .
1&
#6680000
0&
#6690000
b1010 .
1&
b0 G
#6700000
0&
#6710000
b1011 .
1&
#6720000
0&
#6730000
b1100 .
1&
#6740000
0&
#6750000
b1101 .
1&
#6760000
0&
#6770000
b1110 .
1&
#6780000
0&
#6790000
b1111 .
1&
#6800000
0&
#6810000
1/
b0 .
1&
#6820000
0&
#6830000
b1 8
b1010101 ;
0/
b1 .
1&
#6840000
0&
#6850000
b10 .
1&
#6860000
0&
#6870000
b11 .
1&
#6880000
0&
#6890000
b100 .
1&
#6900000
0&
#6910000
b101 .
1&
#6920000
0&
#6930000
b110 .
1&
#6940000
0&
#6950000
b111 .
1&
#6960000
0&
#6970000
b1000 .
1&
#6980000
0&
#6990000
b1001 .
1&
#7000000
0&
#7010000
b1010 .
1&
b1 G
#7020000
0&
#7030000
b1011 .
1&
#7040000
0&
#7050000
b1100 .
1&
#7060000
0&
#7070000
b1101 .
1&
#7080000
0&
#7090000
b1110 .
1&
#7100000
0&
#7110000
b1111 .
1&
#7120000
0&
#7130000
1=
1/
b0 .
1&
#7140000
0&
